collectschedulekgtt.py
collectschedulekgtt-0.0.5.dist-info/WHEEL
collectschedulekgtt-0.0.5.dist-info/METADATA
collectschedulekgtt-0.0.5.dist-info/RECORD
