Metadata-Version: 2.1
Name: collectschedulekgtt
Version: 0.0.5
Summary: Модуль который использует Google таблицу КГТТ , для получения расписания
Author: DaniEruDai
Requires-Python: >=3.10,<4.0
Classifier: Programming Language :: Python :: 3
Classifier: Programming Language :: Python :: 3.10
Requires-Dist: pandas (==1.4.4)
Requires-Dist: recipientgsheets (==0.0.5)
